instr_memory.sv
module instr_memory #(
  parameter ADDR_WIDTH = 32,
  parameter DATA_WIDTH = 32 
)(
  input wire clk,
  input logic [ADDR_WIDTH-1 : 0] Read_address,
  output logic [DATA_WIDTH-1 : 0] Instruction
);

  localparam MEM_SIZE = 2**12; // 4 kiB

  logic [DATA_WIDTH-1 : 0] mem [0 : MEM_SIZE];

  // Inicializa a memória com o conteúdo de um arquivo
  initial begin
    $readmemh("instr_mem.hex", mem, 0, 2); // Carrega o arquivo no intervalo [0, 2]
  end

  // Lógica Sequencial de atribuição das saídas
  always_ff @(posedge clk) begin // reset não implementado
    Instruction <= mem[Read_address];
  end

endmodule

instr_memory_tb.sv
module instr_memory_tb;

  // Parâmetros do módulo
  parameter ADDR_WIDTH = 32;
  parameter DATA_WIDTH = 32;

  // Sinais de entrada/saída
  logic clk;
  logic [ADDR_WIDTH-1 : 0] Read_address;
  logic [DATA_WIDTH-1 : 0] Instruction;

  // Instância do módulo a ser testado
  instr_memory #(
    .ADDR_WIDTH(ADDR_WIDTH),
    .DATA_WIDTH(DATA_WIDTH)
  ) uut (
    .clk(clk),
    .Read_address(Read_address),
    .Instruction(Instruction)
  );

  // Geração do clock
  initial begin
    clk = 0;
    forever #5 clk = ~clk; // Clock com período de 10 unidades de tempo
  end

  // Inicialização do arquivo VCD
  initial begin
    $dumpfile("instr_memory_tb.vcd"); // Nome do arquivo VCD
    $dumpvars(0, instr_memory_tb);    // Salva todas as variáveis do testbench
  end

  // Teste: Listar todo o conteúdo da memória
  initial begin
    // Aguarda a inicialização da memória
    #10;

    // Itera sobre todos os endereços da memória
    for (int i = 0; i < 3; i++) begin
      Read_address = i; // Define o endereço de leitura
      #10; // Aguarda um ciclo de clock para a leitura ser realizada
      $display("Addr: %h, Data: %h", Read_address, Instruction); // Exibe o conteúdo
    end

    // Finaliza a simulação
    $finish;
  end

endmodule

instr_memory_tb.vcd
$date
	Tue Mar 04 23:13:53 2025
$end
$version
	Icarus Verilog
$end
$timescale
	1s
$end
$scope module instr_memory_tb $end
$var wire 32 ! Instruction [31:0] $end
$var parameter 32 " ADDR_WIDTH $end
$var parameter 32 # DATA_WIDTH $end
$var reg 32 $ Read_address [31:0] $end
$var reg 1 % clk $end
$scope module uut $end
$var wire 32 & Read_address [31:0] $end
$var wire 1 % clk $end
$var parameter 32 ' ADDR_WIDTH $end
$var parameter 32 ( DATA_WIDTH $end
$var parameter 32 ) MEM_SIZE $end
$var reg 32 * Instruction [31:0] $end
$upscope $end
$scope begin $ivl_for_loop0 $end
$var integer 32 + i [31:0] $end
$upscope $end
$upscope $end
$enddefinitions $end
$comment Show the parameter values. $end
$dumpall
b1000000000000 )
b100000 (
b100000 '
b100000 #
b100000 "
$end
#0
$dumpvars
b0 +
bx *
bx &
0%
bx $
bx !
$end
#5
1%
#10
0%
b0 $
b0 &
#15
b101 !
b101 *
1%
#20
0%
b1 $
b1 &
b1 +
#25
b1010 !
b1010 *
1%
#30
0%
b10 $
b10 &
b10 +
#35
b1111100 !
b1111100 *
1%
#40
0%
b11 +
